[
  {
    "id": 13,
    "title": "gg",
    "body": "gg",
    "ip": "::1",
    "vote": 8,
    "timestamp": "2025-11-28T09:54:27.932Z",
    "voters": {
      "::1": 1
    }
  },
  {
    "id": 12,
    "title": "111",
    "body": "111",
    "ip": "::1",
    "vote": -1,
    "timestamp": "2025-11-28T09:54:17.888Z",
    "voters": {
      "::1": -1
    }
  },
  {
    "id": 11,
    "title": "gg",
    "body": "gg",
    "ip": "::1",
    "vote": 0,
    "timestamp": "2025-11-28T09:53:53.209Z"
  },
  {
    "id": 10,
    "title": "xytjs",
    "body": "xfyjsxr",
    "ip": "::1",
    "vote": 0,
    "timestamp": "2025-11-28T09:48:06.715Z"
  },
  {
    "id": 9,
    "title": "uu",
    "body": "uu",
    "ip": "::1",
    "vote": 0,
    "timestamp": "2025-11-28T09:46:17.966Z"
  },
  {
    "id": 8,
    "title": "jj",
    "body": "jj",
    "ip": "::1",
    "vote": 0,
    "timestamp": "2025-11-28T09:46:07.838Z"
  },
  {
    "id": 7,
    "title": "yujiyu",
    "body": "yjstyu",
    "ip": "::1",
    "vote": 1,
    "timestamp": "2025-11-28T09:45:52.736Z"
  },
  {
    "id": 6,
    "title": "fgf",
    "body": "fsdfg",
    "ip": "::1",
    "vote": 0,
    "timestamp": "2025-11-28T09:35:30.107Z"
  },
  {
    "id": 5,
    "title": "r",
    "body": "r",
    "ip": "::1",
    "vote": 0,
    "timestamp": "2025-11-28T09:35:19.500Z"
  },
  {
    "id": 4,
    "title": "aleksandrs",
    "body": "123",
    "ip": "::1",
    "vote": 50,
    "timestamp": "2025-11-28T09:07:55.821Z"
  },
  {
    "id": 3,
    "title": "yy",
    "body": "y",
    "ip": "::1",
    "vote": 0,
    "timestamp": "2025-11-28T09:07:04.565Z"
  },
  {
    "id": 2,
    "title": "yy",
    "body": "yy",
    "ip": "::1",
    "vote": 4,
    "timestamp": "2025-11-28T09:06:59.546Z"
  },
  {
    "id": 1,
    "title": "yy",
    "body": "yy",
    "ip": "::1",
    "vote": -4,
    "timestamp": "2025-11-28T09:06:57.262Z"
  }
]